minaki_cli/__init__.py
minaki_cli/cli.py
minaki_cli/commands/__init__.py
minaki_cli/commands/config_cmd.py
minaki_cli/commands/delete_cmd.py
minaki_cli/commands/install_cmd.py
minaki_cli/commands/list_cmd.py
minaki_cli/commands/push_cmd.py
minaki_cli/utils/__init__.py
minaki_cli/utils/config_utils.py
minaki_cli/utils/metadata_utils.py
minaki_apt-0.1.2.dist-info/METADATA
minaki_apt-0.1.2.dist-info/WHEEL
minaki_apt-0.1.2.dist-info/entry_points.txt
minaki_apt-0.1.2.dist-info/top_level.txt
minaki_apt-0.1.2.dist-info/RECORD
