Metadata-Version: 2.1
Name: minaki-apt
Version: 0.1.2
Summary: CLI tool to interact with Minaki APT Repo
Author: MinakiLabs
Classifier: Programming Language :: Python :: 3
Classifier: Operating System :: OS Independent
Requires-Dist: click
Requires-Dist: requests
Requires-Dist: yaspin
